codex/__init__.py
codex/codex_kg.py
codex/codex_query.py
codex/codex_query_builder.py
codex/grakn_functions.py
grakn_codex-0.0.3.dist-info/LICENSE
grakn_codex-0.0.3.dist-info/METADATA
grakn_codex-0.0.3.dist-info/WHEEL
grakn_codex-0.0.3.dist-info/top_level.txt
grakn_codex-0.0.3.dist-info/RECORD
