Metadata-Version: 2.1
Name: grakn-codex
Version: 0.0.3
Summary: Codex is a Python package that provides a simple, yet powerful API designed to make working with the Grakn knowledge graph intuitive
Home-page: https://github.com/banjtheman/grakn-codex
Author: Banjo Obayomi
Author-email: banjtheman@gmail.com
License: UNKNOWN
Keywords: python,knowledge graph,grakn,nlp,database
Platform: UNKNOWN
Classifier: Development Status :: 5 - Production/Stable
Classifier: Intended Audience :: Developers
Classifier: Natural Language :: English
Classifier: Programming Language :: Python
Classifier: Programming Language :: Python :: 3
Classifier: Programming Language :: Python :: 3.6
Classifier: Programming Language :: Python :: 3.7
Classifier: Programming Language :: Python :: 3.8
Requires-Python: >3.6
